multi_agent_power_allocation/__init__.py
multi_agent_power_allocation/algorithms/__init__.py
multi_agent_power_allocation/algorithms/algorithm_register.py
multi_agent_power_allocation/algorithms/high_level/__init__.py
multi_agent_power_allocation/algorithms/high_level/dqn.py
multi_agent_power_allocation/algorithms/high_level/high_level_algorithm.py
multi_agent_power_allocation/algorithms/high_level/random.py
multi_agent_power_allocation/algorithms/high_level/raql.py
multi_agent_power_allocation/algorithms/high_level/sacpa.py
multi_agent_power_allocation/algorithms/high_level/sacpf.py
multi_agent_power_allocation/algorithms/low_level/__init__.py
multi_agent_power_allocation/algorithms/low_level/dqn.py
multi_agent_power_allocation/algorithms/low_level/low_level_algorithm.py
multi_agent_power_allocation/algorithms/low_level/random.py
multi_agent_power_allocation/algorithms/low_level/raql.py
multi_agent_power_allocation/algorithms/low_level/sac.py
multi_agent_power_allocation/algorithms/low_level/utils/__init__.py
multi_agent_power_allocation/algorithms/low_level/utils/replay_buffer.py
multi_agent_power_allocation/img/AP.png
multi_agent_power_allocation/img/device.png
multi_agent_power_allocation/nn/module.py
multi_agent_power_allocation/nn/summarize_models.txt
multi_agent_power_allocation/run/__init__.py
multi_agent_power_allocation/run/benchmark.py
multi_agent_power_allocation/run/default_config.yaml
multi_agent_power_allocation/run/test.py
multi_agent_power_allocation/run/train.py
multi_agent_power_allocation/run/tune.py
multi_agent_power_allocation/utils/__init__.py
multi_agent_power_allocation/utils/evaluator.py
multi_agent_power_allocation/utils/logger.py
multi_agent_power_allocation/utils/multi_agent.py
multi_agent_power_allocation/utils/plot.py
multi_agent_power_allocation/utils/train_config.py
multi_agent_power_allocation/utils/trainer.py
multi_agent_power_allocation/wireless_environment/constants.py
multi_agent_power_allocation-1.0.0.dist-info/METADATA
multi_agent_power_allocation-1.0.0.dist-info/WHEEL
multi_agent_power_allocation-1.0.0.dist-info/entry_points.txt
multi_agent_power_allocation-1.0.0.dist-info/licenses/LICENSE
multi_agent_power_allocation-1.0.0.dist-info/RECORD
