Metadata-Version: 2.4
Name: multi-agent-power-allocation
Version: 1.0.0
Summary: Multi-agent power allocation with DRL
License-File: LICENSE
Author: Nguyen Duc Tai
Author-email: ductaingn.015203@gmail.com
Requires-Python: ==3.11.13
Classifier: Programming Language :: Python :: 3
Requires-Dist: attrs (==25.3.0)
Requires-Dist: matplotlib (>=3.10.6,<4.0.0)
Requires-Dist: numpy (==1.26.4)
Requires-Dist: pettingzoo (>=1.25.0,<2.0.0)
Requires-Dist: plotly (==6.2.0)
Requires-Dist: pygame (==2.6.1)
Requires-Dist: rich (>=14.1.0,<15.0.0)
Requires-Dist: torch (==2.6.0)
Requires-Dist: torchaudio (==2.6.0)
Requires-Dist: torchinfo (>=1.8.0,<2.0.0)
Requires-Dist: torchvision (==0.21.0)
Requires-Dist: tqdm (>=4.67.1,<5.0.0)
Requires-Dist: wandb (==0.19.11)
